cesnet_models/__init__.py
cesnet_models/_models_meta.py
cesnet_models/constants.py
cesnet_models/helpers.py
cesnet_models/models.py
cesnet_models/transforms.py
cesnet_models/architectures/__init__.py
cesnet_models/architectures/cnn_resblock.py
cesnet_models/architectures/embedding_model_wrapper.py
cesnet_models/architectures/multimodal_cesnet.py
cesnet_models/architectures/multimodal_cesnet_enhanced.py
cesnet_models-0.4.1.dist-info/licenses/LICENCE
cesnet_models-0.4.1.dist-info/METADATA
cesnet_models-0.4.1.dist-info/WHEEL
cesnet_models-0.4.1.dist-info/top_level.txt
cesnet_models-0.4.1.dist-info/RECORD
