Metadata-Version: 2.4
Name: cesnet-models
Version: 0.4.1
Summary: Pre-trained neural networks for encrypted traffic classification
Author-email: Jan Luxemburk <luxemburk@cesnet.cz>, Karel Hynek <hynekkar@cesnet.cz>
Maintainer-email: Jan Luxemburk <luxemburk@cesnet.cz>, Karel Hynek <hynekkar@cesnet.cz>
License-Expression: BSD-3-Clause
Project-URL: Homepage, https://github.com/CESNET/cesnet-models
Project-URL: Documentation, https://cesnet.github.io/cesnet-models/
Project-URL: Bug Tracker, https://github.com/CESNET/cesnet-models/issues
Keywords: traffic classification,deep learning,models
Classifier: Programming Language :: Python :: 3.10
Classifier: Intended Audience :: Science/Research
Classifier: Operating System :: OS Independent
Requires-Python: >=3.10
License-File: LICENCE
Requires-Dist: numpy
Requires-Dist: scikit-learn
Requires-Dist: torch>=1.10
Provides-Extra: dev
Requires-Dist: build; extra == "dev"
Requires-Dist: mkdocs-autorefs; extra == "dev"
Requires-Dist: mkdocs-material-extensions; extra == "dev"
Requires-Dist: mkdocs-material; extra == "dev"
Requires-Dist: mkdocs; extra == "dev"
Requires-Dist: mkdocstrings-python; extra == "dev"
Requires-Dist: mkdocstrings; extra == "dev"
Requires-Dist: twine; extra == "dev"
Dynamic: license-file
